health_check/__init__.py
health_check/check.py
health_check_package-0.0.4.5.dist-info/LICENSE
health_check_package-0.0.4.5.dist-info/METADATA
health_check_package-0.0.4.5.dist-info/WHEEL
health_check_package-0.0.4.5.dist-info/top_level.txt
health_check_package-0.0.4.5.dist-info/RECORD
