Metadata-Version: 2.1
Name: health-check-package
Version: 0.0.4.5
Summary: This is the celery health-check package
Home-page: UNKNOWN
Author: mahiman
Author-email: mahiman@betterhalf.ai
License: UNKNOWN
Platform: UNKNOWN
License-File: LICENSE
